{
    "title": "asd",
    "instructions": "",
    "timeLimit": null,
    "allowedAttempts": 1,
    "scoreToKeep": "highest",
    "questions": [
        {
            "id": "q1755500822811-1",
            "index": 1,
            "type": "mcq",
            "title": "",
            "text": "<p>asd<\/p>",
            "points": 1,
            "createdAt": 1755500822811,
            "options": [
                {
                    "text": "asd",
                    "is_correct": true
                },
                {
                    "text": "asd",
                    "is_correct": false
                }
            ],
            "allow_multiple": false,
            "blanks": [],
            "variables": [],
            "formula": {
                "expression": "",
                "decimals": 2
            },
            "sample_output": ""
        }
    ],
    "metadata": {
        "id": "quiz_68a2d11f9f2f27.09321643",
        "created": "2025-08-18 09:07:11",
        "lastModified": "2025-08-18 09:07:11"
    }
}